Metadata-Version: 1.0
Name: prettydataloader
Version: 0.1.1
Summary: Pretty Data Loader
Home-page: https://github.com/summer4an
Author: Atsushi Nakajima
Author-email: summer4an@gmail.com
License: MIT
Platform: UNKNOWN
